<!--
The biblioentry attributes id the biblioentry attributes id is the
surname of the first author immediately followed by the last two
numbers of the publishing year. If this leads to non-unique ids a
lower case letter is appended in alphabetical order starting with the
second id.

Please insert new entries in alphabetical order given by the
biblioentry attribute id.

Supported elements are:
authorgroup, author, title, subtitle, volumenum, edition, copyright,
publisher, pubdate, pagenums, isbn, issn, pubsnumber

This may be used as a template:
  <biblioentry id="" xreflabel="">
   <authorgroup>
    <author>
     <firstname></firstname>
     <surname></surname>
    </author>
   </authorgroup>
   <title>
   </title>
   <edition></edition>
   <publisher>
   </publisher>
   <volumenum></volumenum>
   <pagenums></pagenums>
   <pubdate></pubdate>
  </biblioentry>
-->

<bibliography>
 <title>Bibliography</title>
 <bibliodiv>
  <title>References </title>

  <biblioentry id="Baeck93" xreflabel="Baeck93">
   <authorgroup>
    <author>
     <firstname>T.</firstname>
     <surname>Bäck</surname>
    </author>
    <author>
     <firstname>H.-P.</firstname>
     <surname>Schwefel</surname>
    </author>
   </authorgroup>
   <title>
   An overview of evolutionary algorithms for parameter optimization
   </title>
   <publisher> Evolutionary Computation </publisher>
   <volumenum>1</volumenum>
   <pagenums>1 - 23</pagenums>
   <pubdate>1997</pubdate>
  </biblioentry>

  <biblioentry id="Baeck97" xreflabel="Baeck97">
   <authorgroup>
    <author>
     <firstname>T.</firstname>
     <surname>Bäck</surname>
    </author>
    <author>
     <firstname>D.B.</firstname>
     <surname>Fogel</surname>
    </author>
    <author>
     <firstname>Z.</firstname>
     <surname>Michalewicz</surname>
    </author>
   </authorgroup>
   <title>
   Handbook of evolutionary computation
   </title>
   <publisher>Oxford: IOP Publishing/Oxford University Press </publisher>
   <pubdate>1997</pubdate>
  </biblioentry>

  <biblioentry id="Bell66" xreflabel="Bell66">
   <authorgroup>
    <author>
     <firstname>M.</firstname>
     <surname>Bell</surname>
    </author>
    <author>
     <firstname>M.C.</firstname>
     <surname>Pike</surname>
    </author>
   </authorgroup>
   <title>Remark on algorithm 178 direct search</title>
   <publisher>
   Communications of the Association for Computing Machinery </publisher>
   <volumenum>9</volumenum>
   <pagenums>684 - 685</pagenums>
   <pubdate>1966</pubdate>
  </biblioentry>

  <biblioentry id="Fletcher87" xreflabel="Fletcher87">
   <author>
    <firstname>R.</firstname>
    <surname>Fletcher</surname>
   </author>
   <title>
   Practical methods of optimization
   </title>
   <edition>2nd Edition</edition>
   <publisher>
   Chichester: John Wiley &amp; Sons </publisher>
   <pubdate>1987</pubdate>
  </biblioentry>

  <biblioentry id="Fogel92" xreflabel="Fogel92">
   <authorgroup>
    <author>
     <firstname>D.B.</firstname>
     <surname>Fogel</surname>
    </author>
    <author>
     <firstname>L.J.</firstname>
     <surname>Fogel</surname>
    </author>
    <author>
     <firstname>J.W.</firstname>
     <surname>Atmar</surname>
    </author>
   </authorgroup>
   <title>
   Meta-evolutionary programming
   </title>
   <publisher>
   25th Asiloma Conference on Signals, Systems and Computers. IEEE
   Computer Society, Asilomar
   </publisher>
   <pagenums>540 - 545</pagenums>
   <pubdate>1992</pubdate>
  </biblioentry>

  <biblioentry id="Gibson00" xreflabel="Gibson00">
   <authorgroup>
    <author>
     <firstname>M.A.</firstname>
     <surname>Gibson</surname>
    </author>
    <author>
     <firstname>J.</firstname>
     <surname>Bruck</surname>
    </author>
   </authorgroup>
   <title>
    Efficient Exact Stochastic Simulation of Chemical Systems with
 Many Species and Many Channels
   </title>
   <publisher>J. Phys. Chem. </publisher>
   <volumenum>A104(9)</volumenum>
   <pagenums>1876-1889</pagenums>
   <pubdate>2000</pubdate>
  </biblioentry>

  <biblioentry id="Gillespie76" xreflabel="Gillespie76">
   <author>
    <firstname>D.T.</firstname>
    <surname>Gillespie</surname>
   </author>
   <title>
    A General Method for Numerically Simulating the Stochastic Time
 Evolution of Coupled Chemical Reactions
   </title>
   <publisher>J. Comp. Phys. </publisher>
   <volumenum>22</volumenum>
   <pagenums>403 - 434</pagenums>
   <pubdate>1976</pubdate>
  </biblioentry>

  <biblioentry id="Goldberg89" xreflabel="Goldberg89">
   <author>
    <firstname>D.E.</firstname>
    <surname>Goldberg</surname>
   </author>
   <title>
    Genetic algorithms in search, optimization and machine learning
   </title>
   <publisher>Addison-Wesley, Reading, Mass. </publisher>
   <pubdate>1989</pubdate>
  </biblioentry>

  <biblioentry id="Goldfeld66" xreflabel="Goldfeld66">
   <authorgroup>
    <author>
     <firstname>S. M.</firstname>
     <surname>Goldfeld</surname>
    </author>
    <author>
     <firstname>R. E.</firstname>
     <surname>Quant</surname>
    </author>
    <author>
     <firstname>H. F.</firstname>
     <surname></surname>
    </author>
   </authorgroup>
   <title>
   Maximisation by quadratic hill-climbing
   </title>
   <publisher>Econometrica </publisher>
   <volumenum>34</volumenum>
   <pagenums>541 - 555</pagenums>
   <pubdate>1966</pubdate>
  </biblioentry>

  <biblioentry id="Hindmarsh83" xreflabel="Hindmarsh83">
   <author>
    <firstname>A.C.</firstname>
    <surname>Hindmarsh</surname>
   </author>
   <title>
    ODEPACK, A Systematized Collection of ODE Solvers
   </title>
   <publisher>Scientific Computing, R. S. Stepleman et al. (eds.),
    North-Holland, Amsterdam, IMACS Transactions on Scientific
    Computation </publisher>
   <volumenum>1</volumenum>
   <pagenums>55 - 64</pagenums>
   <pubdate>1983</pubdate>
  </biblioentry>

  <biblioentry id="Hooke61" xreflabel="Hooke61">
   <authorgroup>
    <author>
     <firstname>R.</firstname>
     <surname>Hooke</surname>
    </author>
    <author>
     <firstname>T. A.</firstname>
     <surname>Jeeves</surname>
    </author>
   </authorgroup>
   <title>
    "Direct search" solution of numerical and statistical problems
   </title>
   <publisher>Journal of the Association for Computing Machinery </publisher>
   <volumenum>8</volumenum>
   <pagenums>212 - 229</pagenums>
   <pubdate>1961</pubdate>
  </biblioentry>

  <biblioentry id="Kaupe63" xreflabel="Kaupe63">
   <author>
    <firstname></firstname>
    <surname>Kaupe</surname>
   </author>
   <title>Algorithm 178 direct search</title>
   <publisher>
   Communications of the Association of Computing Machinery 
   </publisher>
   <volumenum>6</volumenum>
   <pagenums>313 - 314</pagenums>
   <pubdate>1963</pubdate>
  </biblioentry>

  <biblioentry id="Levenberg44" xreflabel="Levenberg44">
   <author>
    <firstname>K.</firstname>
    <surname>Levenberg</surname>
   </author>
   <title>
   A method for the solution of certain nonlinear problems in least squares
   </title>
   <publisher>Quart. Appl. Math. </publisher>
   <volumenum>2</volumenum>
   <pagenums>164 - 168</pagenums>
   <pubdate>1944</pubdate>
  </biblioentry>

  <biblioentry id="Maier91" xreflabel="Maier91">
   <author>
    <firstname>W.L.</firstname>
    <surname>Maier</surname>
   </author>
   <title>
    A Fast Pseudo Random Number Generator
   </title>
   <publisher>Dr. Dobb's Journal </publisher>
   <volumenum>May</volumenum>
   <pagenums>152 - 157</pagenums>
   <pubdate>1991</pubdate>
  </biblioentry>

  <biblioentry id="Marquardt63" xreflabel="Marquardt63">
   <author>
    <firstname>D.W.</firstname>
    <surname>Marquardt</surname>
   </author>
   <title>
    An algorithm for least squares estimation of nonlinear parameters
   </title>
   <publisher>SIAM Journal </publisher>
   <volumenum>11</volumenum>
   <pagenums>431 - 441</pagenums>
   <pubdate>1963</pubdate>
  </biblioentry>

  <biblioentry id="Matsumoto98" xreflabel="Matsumoto98">
   <authorgroup>
    <author>
     <firstname>M.</firstname>
     <surname>Matsumoto</surname>
    </author>
    <author>
     <firstname>T.</firstname>
     <surname>Nishimura</surname>
    </author>
   </authorgroup>
   <title>
    Mersenne twister: A 623-dimensionally equidistributed uniform
     pseudorandom number generator
   </title>
   <publisher>ACM Trans. on Modeling and Computer Simulations </publisher>
   <volumenum>8</volumenum>
   <pagenums>3 - 30</pagenums>
   <pubdate>1998</pubdate>
  </biblioentry>

  <biblioentry id="Michalewicz94" xreflabel="Michalewicz94">
   <author>
    <firstname>Z.</firstname>
    <surname>Michalewicz</surname>
   </author>
   <title>
   Genetic algorithms + data structures = evolution programs
   </title>
   <edition>3rd Edition</edition>
   <publisher>Springer-Verlag, Berlin. </publisher>
   <pubdate>1994</pubdate>
  </biblioentry>

  <biblioentry id="Mitchell95" xreflabel="Mitchell95">
   <author>
    <firstname>M.</firstname>
    <surname>Mitchell</surname>
   </author>
   <title>
    An Introduction to Genetic Algorithms
   </title>
   <publisher>MIT Press, Boston. </publisher>
   <pubdate>1995</pubdate>
  </biblioentry>

  <biblioentry id="Petzold83" xreflabel="Petzold83">
   <author>
    <firstname>L.</firstname>
    <surname>Petzold</surname>
   </author>
   <title>
    Automatic selection of methods for solving stiff and nonstiff
     systems of ordinary differential equations. 
   </title>
   <publisher>SIAM J. Sci. Stat. Comput. </publisher>
   <volumenum>4</volumenum>
   <pagenums>136 - 148</pagenums>
   <pubdate>1983</pubdate>
  </biblioentry>

  <biblioentry id="Runarsson00" xreflabel="Runarsson00">
   <authorgroup>
    <author>
     <firstname>T.</firstname>
     <surname>Runarsson</surname>
    </author>
    <author>
     <firstname>X.</firstname>
     <surname>Yao</surname>
    </author>
   </authorgroup>
   <title>
   Stochastic ranking for constrained evolutionary optimization
   </title>
   <publisher>EEE Transactions on Evolutionary Computation </publisher>
   <volumenum>4</volumenum>
   <pagenums>284 - 294</pagenums>
   <pubdate>2000</pubdate>
  </biblioentry>

  <biblioentry id="Swann72" xreflabel="Swann72">
   <author>
    <firstname>W.H.</firstname>
    <surname>Swann</surname>
   </author>
   <title>Direct search methods</title>
   <publisher>
   Numerical methods for unconstrained optimization., W. Murray, ed.
   (London &amp; New York: Academic Press)
   </publisher>
   <pagenums>13 - 28</pagenums>
   <pubdate>1972</pubdate>
  </biblioentry>

  <biblioentry id="Vallabhajosyula06" xreflabel="Vallabhajosyula06">
    <authorgroup>
      <author>
        <firstname>R. R.</firstname>
        <surname>Vallabhajosyula</surname>
      </author>
      <author>
        <firstname>V.</firstname>
        <surname>Chickarmane</surname>
      </author>
      <author>
        <firstname>H. M.</firstname>
        <surname>Sauro</surname>
      </author>
    </authorgroup>
    <title>
      Conservation analysis of large biochemical networks
    </title>
    <publisher>
      Bioinformatics
    </publisher>
    <volumenum>22(3)</volumenum>
    <pagenums>346 - 353</pagenums>
    <pubdate>2006</pubdate>
  </biblioentry>
  

  
  <biblioentry id="Wolf85" xreflabel="Wolf85">
    <authorgroup>
      <author>
        <firstname>A.</firstname>
        <surname>Wolf</surname>
      </author>
      <author>
        <firstname>J. B.</firstname>
        <surname>Swift</surname>
      </author>
      <author>
        <firstname>H.</firstname>
        <surname>Swinney</surname>
      </author>
      <author>
        <firstname>J. A.</firstname>
        <surname>Vastano</surname>
      </author>
    </authorgroup>
    <title>
      Determining Lyapunov exponents from a time series
    </title>
    <publisher>
      Physika
    </publisher>
    <volumenum>16D</volumenum>
    <pagenums>285 - 317</pagenums>
    <pubdate>1985</pubdate>
  </biblioentry>
  
  
 </bibliodiv>
</bibliography>
